{
	"1.c": 							"This json info file explains the forcing variables and all related information",
	"2.c":							"add more comments",
	"3.c":							"and some more",

	"funName":
	{
		"import": "readForcing",
		"check": "checkInputData"
	},
	"comments": "to get forcing from netCDF file",
	"size": [Inf, Inf],
	"oneDataPath": "data/input/FluxNet_Ex/US-Blo.2000-2015.nc",
	"variables": {

	"PET":
	{
		"variableUnit": "mm d-1",
		"bounds": [0, 100],
		"sourceVariableName": "PET",
		"sourceVariableUnit": "mm d-1",
		"source2sindbadUnit": "*1",
		"isCategorical": false,
		"nameShort": "PET",
		"spaceTimeType": "normal",
		"sourceDataProductName": "FLUXNET",
		"dataPath": "data/input/FluxNet_Ex/US-Blo.2000-2015.nc"
	},
	"Rain":
    {
		"variableUnit": "mm d-1",
		"bounds": [0, 100],
		"sourceVariableName": "P",
		"sourceVariableUnit": "mm d-1",
		"source2sindbadUnit": "*1",
		"isCategorical": false,
		"nameShort": "Rain",
		"spaceTimeType": "normal",
		"sourceDataProductName": "FLUXNET",
		"dataPath": "data/input/FluxNet_Ex/US-Blo.2000-2015.nc"
	},
	"Rg":
    {
		"variableUnit": "MJ m-2",
		"bounds": [0, 600],
		"sourceVariableName": "SW_IN",
		"sourceVariableUnit": "W m-2",
		"source2sindbadUnit": "/11.57407",
		"isCategorical": false,
		"nameShort": "Global Radiation",
		"spaceTimeType": "normal",
		"sourceDataProductName": "FLUXNET",
		"dataPath": "data/input/FluxNet_Ex/US-Blo.2000-2015.nc"
	},
	"PAR":
    {
		"variableUnit": "MJ m-2",
		"bounds": [0, 600],
		"sourceVariableName": "SW_IN",
		"sourceVariableUnit": "W m-2",
		"source2sindbadUnit": "*0.5/11.57407",
		"isCategorical": false,
		"nameShort": "Photosynthetically active radiation (=Rg*.5)",
		"spaceTimeType": "normal",
		"sourceDataProductName": "FLUXNET",
		"dataPath": "data/input/FluxNet_Ex/US-Blo.2000-2015.nc"
	},
	"RgPot":
    {
		"variableUnit": "MJ m-2",
		"bounds": [0, 600],
		"sourceVariableName": "SW_IN_pot",
		"sourceVariableUnit": "W m-2",
		"source2sindbadUnit": "/11.57407",
		"isCategorical": false,
		"nameShort": "Potential Global Radiation",
		"spaceTimeType": "normal",
		"sourceDataProductName": "FLUXNET",
		"dataPath": "data/input/FluxNet_Ex/US-Blo.2000-2015.nc"
	},
	"Rn":
    {
		"variableUnit": "MJ m-2",
		"bounds": [-50, 500],
		"sourceVariableName": "NETRAD",
		"sourceVariableUnit": "W m-2",
		"source2sindbadUnit": "/11.57407",
		"isCategorical": false,
		"nameShort": "Net radiation",
		"spaceTimeType": "normal",
		"sourceDataProductName": "FLUXNET",
		"dataPath": "data/input/FluxNet_Ex/US-Blo.2000-2015.nc"
	},
	"Tair":
    {
		"variableUnit": "째C",
		"bounds": [-80, 60],
		"sourceVariableName": "TA",
		"sourceVariableUnit": "째C",
		"source2sindbadUnit": "*1",
		"isCategorical": false,
		"nameShort": "Tair",
		"spaceTimeType": "normal",
		"sourceDataProductName": "FLUXNET",
		"dataPath": "data/input/FluxNet_Ex/US-Blo.2000-2015.nc"
	},
	"TairDay":
    {
		"variableUnit": "째C",
		"bounds": [-80, 60],
		"sourceVariableName": "TA",
		"sourceVariableUnit": "째C",
		"source2sindbadUnit": "*1",
		"isCategorical": false,
		"nameShort": "TairDay",
		"spaceTimeType": "normal",
		"sourceDataProductName": "FLUXNET",
		"dataPath": "data/input/FluxNet_Ex/US-Blo.2000-2015.nc"
	},
	"VPD":
    {
		"variableUnit": "hPa",
		"bounds": [0, 100],
		"sourceVariableName": "VPD",
		"sourceVariableUnit": "hPa",
		"source2sindbadUnit": "*1",
		"isCategorical": false,
		"nameShort": "Vapor pressure deficit Day",
		"spaceTimeType": "normal",
		"sourceDataProductName": "FLUXNET",
		"dataPath": "data/input/FluxNet_Ex/US-Blo.2000-2015.nc"
	},
	"VPDDay":
    {
		"variableUnit": "hPa",
		"bounds": [0, 100],
		"sourceVariableName": "VPD",
		"sourceVariableUnit": "hPa",
		"source2sindbadUnit": "*1",
		"isCategorical": false,
		"nameShort": "Vapor pressure deficit Day",
		"spaceTimeType": "normal",
		"sourceDataProductName": "FLUXNET",
		"dataPath": "data/input/FluxNet_Ex/US-Blo.2000-2015.nc"
	},
	"fAPAR":
    {
		"variableUnit": "-",
		"bounds": [0, 1],
		"sourceVariableName": "ndvi",
		"sourceVariableUnit": "-",
		"source2sindbadUnit": "*1",
		"isCategorical": false,
		"nameShort": "fAPAR from ndvi",
		"spaceTimeType": "normal",
		"sourceDataProductName": "FLUXNET",
		"dataPath": "data/input/FluxNet_Ex/US-Blo.2000-2015.nc"
	},
	"LAI":
    {
		"variableUnit": "-",
		"bounds": [0, 1],
		"sourceVariableName": "ndvi",
		"sourceVariableUnit": "-",
		"source2sindbadUnit": "*10",
		"isCategorical": false,
		"nameShort": "LAI = 10 x ndvi",
		"spaceTimeType": "normal",
		"sourceDataProductName": "FLUXNET",
		"dataPath": "data/input/FluxNet_Ex/US-Blo.2000-2015.nc"
	},
	"NDVI":
    {
		"variableUnit": "-",
		"bounds": [0, 1],
		"sourceVariableName": "ndvi",
		"sourceVariableUnit": "-",
		"source2sindbadUnit": "*1",
		"isCategorical": false,
		"nameShort": "Normalized vegetation difference index",
		"spaceTimeType": "normal",
		"sourceDataProductName": "FLUXNET",
		"dataPath": "data/input/FluxNet_Ex/US-Blo.2000-2015.nc"
	},
	"NDWI":
    {
		"variableUnit": "-",
		"bounds": [0, 1],
		"sourceVariableName": "ndwi",
		"sourceVariableUnit": "-",
		"source2sindbadUnit": "*1",
		"isCategorical": false,
		"nameShort": "Normalized water difference index",
		"spaceTimeType": "normal",
		"sourceDataProductName": "FLUXNET",
		"dataPath": "data/input/FluxNet_Ex/US-Blo.2000-2015.nc"
	}
}
}
