{
	"dimensions": {
		"permute": null,
		"space": ["latitude", "longitude"],
		"time": "time"
	},
	"sel_mask": null,
	"default_forcing": {
		"variable_unit": null,
		"bounds": [],
		"source_variable_name": null,
		"source_variable_unit": null,
		"name_short": null,
		"source_to_sindbad_unit": 1.0,
		"additive_unit_conversion": false,
		"is_categorical": false,
		"depth_dimension": null,
		"space_time_type": "spatiotemporal",
		"source_product_name": "FLUXNET",
		"data_path": "../data/DE-All.1979.2017.daily.nc"
	},
	"variables": {
	"ambient_CO2":
    {
		"variable_unit": "ppm",
		"bounds": [200.0, 500.0],
		"source_variable_name": "atmCO2_SCRIPPS_global",
		"source_variable_unit": "ppm",
		"name_short": "ambCO2"
	},
	"Rain":
    {
		"variable_unit": "mm d-1",
		"bounds": [0.0, 300.0],
		"source_variable_name": "P_ERAIv2_gfld",
		"source_variable_unit": "mm d-1",
		"name_short": "Rain"
	},
	"Rg":
    {
		"variable_unit": "MJ m-2 d-1",
		"bounds": [0.0, 100.0],
		"source_variable_name": "SW_IN_ERAIv2_gfld",
		"source_variable_unit": "MJ m-2 d-1",
		"name_short": "Global Radiation"
	},
	"PAR":
    {
		"variable_unit": "MJ m-2 d-1",
		"bounds": [0.0, 50.0],
		"source_variable_name": "SW_IN_ERAIv2_gfld",
		"source_variable_unit": "MJ m-2 d-1",
		"source_to_sindbad_unit": 0.50,
		"name_short": "Photosynthetically active radiation (=Rg*.5)"
	},
	"RgPot":
    {
		"variable_unit": "MJ m-2 d-1",
		"bounds": [0.0, 100.0],
		"source_variable_name": "SW_IN_POT_ONEFlux",
		"source_variable_unit": "MJ m-2 d-1",
		"name_short": "Potential Global Radiation"
	},
	"Rn":
    {
		"variable_unit": "MJ m-2 d-1",
		"bounds": [0.0, 100.0],
		"source_variable_name": "NETRAD_ERAIv2_gfld",
		"source_variable_unit": "MJ m-2 d-1",
		"name_short": "Net radiation"
	},
	"dist_intensity":
    {
		"variable_unit": null,
		"bounds": [-0.001, 1.1],
		"source_variable_name": "dist_frac_sb2018",
		"source_variable_unit": null,
		"is_categorical": true,
		"name_short": "isDisturbed flag for disturbance",
		"source_product_name": "Besnard2018"
	},
	"Tair":
    {
		"variable_unit": "째C",
		"bounds": [-80.0, 60.0],
		"source_variable_name": "TA_ERAIv2_gfld",
		"source_variable_unit": "째C",
		"name_short": "Tair"
	},
	"TairDay":
    {
		"variable_unit": "째C",
		"bounds": [-80.0, 60.0],
		"source_variable_name": "TA_DayTime_ERAIv2_gfld",
		"source_variable_unit": "째C",
		"name_short": "TairDay"
	},
	"VPD":
    {
		"variable_unit": "kPa",
		"bounds": [0.01, 100.0],
		"source_variable_name": "VPD_ERAIv2_gfld",
		"source_variable_unit": "Pa",
		"source_to_sindbad_unit": 0.001,
		"name_short": "Vapor pressure deficit"
	},
	"VPDDay":
    {
		"variable_unit": "kPa",
		"bounds": [0.01, 100.0],
		"source_variable_name": "VPD_DayTime_ERAIv2_gfld",
		"source_variable_unit": "Pa",
		"source_to_sindbad_unit": 0.001,
		"name_short": "Vapor pressure deficit Day"
	},
	"CLAY": {
		"variable_unit": "-",
		"bounds": [0.0, 100.0],
		"source_variable_name": "CLYPPT_SoilGrids",
		"source_variable_unit": "%",
		"source_to_sindbad_unit": 0.01,
		"name_short": "CLAY",
		"space_time_type": "spatiovertical",
		"source_product_name": "soilgrids"
	}
	,
	"SAND": {
		"variable_unit": "-",
		"bounds": [0.0, 100.0],
		"source_variable_name": "SNDPPT_SoilGrids",
		"source_variable_unit": "%",
		"source_to_sindbad_unit": 0.01,
		"name_short": "SAND",
		"space_time_type": "spatiovertical",
		"source_product_name": "soilgrids"
	},
	"SILT": {
		"variable_unit": "-",
		"bounds": [0.0, 100.0],
		"source_variable_name": "SLTPPT_SoilGrids",
		"source_variable_unit": "%",
		"source_to_sindbad_unit": 0.01,
		"name_short": "CLAY",
		"space_time_type": "spatiovertical",
		"source_product_name": "soilgrids"
	},
	"ORGM": {
		"variable_unit": "-",
		"bounds": [0.0, 100.0],
		"source_variable_name": "OCSTHA_SoilGrids",
		"source_variable_unit": "%",
		"source_to_sindbad_unit": 0.0,
		"name_short": "CLAY",
		"space_time_type": "spatiovertical",
		"source_product_name": "soilgrids"
	}
}
}