{

	"time":
	{
		"model_time_step": 			"daily",
		"start_date": 				"1979-01-01",
		"end_date": 				"2017-12-31",
		"timesteps_in_day": 		1,
		"timesteps_in_year": 		365
	},
	"mapping": {
		"yaxarray": [],
		"run_ecosystem": ["time", "longitude", "latitude"],
		"parallelization": "qbmap"
	},
	"flags":
	{
		"save_info": 			true,
		"debug_model": 			false, 
		"catch_model_errors": 	false,
		"run_spinup":            false,
		"run_forward": 			true,
		"run_update_mdels": 	false,
		"run_optimization": 	true,
		"run_forward_and_cost":	true
	},
	"rules":
	{
		"verbosity": 5,
		"model_array_type": "staticarray",
		"forward_diff": false,
		"data_type": "Float32",
		"data_backend": "yaxarray",
		"tolerance": 1.0e-2,
		"yax_max_cache": 2e9
	},
	"output": {
		"output_array_type": "array",		
		"all": true,
		"path": null,
		"format": ".zarr",
		"depth_dimensions":{
			"d_soil": "soilW",
			"d_tws": "TWS",
			"d_cEco": 8,
			"d_snow": "snowW"
		},
		"variables": {
			"fluxes.evapotranspiration": null,
			"fluxes.transpiration": null,
			"fluxes.runoff": null,
			"fluxes.surface_runoff": null,
			"fluxes.gpp": null,
			"fluxes.nee": null,
			"pools.TWS": "d_tws",
			"pools.soilW": "d_soil",
			"pools.cEco": "d_cEco",
			"waterBalance.water_balance": null
		}
	}
}
