{"Input":{"VariableName":[],"Name":[],"Unit":[],"Dimensions":[],"Source":[],"Comment":[]},"Params":{"VariableName":["PFT","TreeCover"],"Name":[NaN,NaN],"Unit":["class","[]"],"Default":[1,1],"LowerBound":[NaN,NaN],"UpperBound":[NaN,NaN],"Distribution":[NaN,NaN],"p1":[NaN,NaN],"p2":[NaN,NaN],"p3":[NaN,NaN],"p4":[NaN,NaN],"p5":[NaN,NaN],"Comment":[NaN,NaN]},"Output":{"VariableName":[],"Name":[],"Unit":[],"Destiny":[],"KeepAlways":[],"Comment":[]},"Main":{"Purpose":[],"FunctionHandle":[],"Path":[]}}