{
    "params": {
        "qt": {
            "Name": "delay parameter for land runoff",
            "Unit": "time",
            "Default": 2,
            "LowerBound": 0.5,
            "UpperBound": 100,
            "Distribution": {
                "name": "uniform",
                "funHandle": "",
                "params": []
            },
            "Comment": "in Paper: q_t"
        }
    },
    "devStage": {
        "experimental": true,
        "tested": false,
        "consolidated": false,
        "published": false,
        "comment": "experimental: try-out, tested: runs and produces sane output, consolidated: tested and used for scientific purpose, published: for published approach"
    }
}